ChangeLog.rst
LICENSE.txt
MANIFEST.in
README.rst
setup.py
radmyarchive/__init__.py
radmyarchive/radmyarchiveexceptions.py
radmyarchive.egg-info/PKG-INFO
radmyarchive.egg-info/SOURCES.txt
radmyarchive.egg-info/dependency_links.txt
radmyarchive.egg-info/requires.txt
radmyarchive.egg-info/top_level.txt
scripts/RADMYARCHIVE.py