Metadata-Version: 1.1
Name: radmyarchive
Version: 1.1.1
Summary: A simple photo rearranger with help of EXIF tags
Home-page: https://github.com/usta/radmyarchive-py
Author: Ömer Fadıl Usta
Author-email: omerusta@gmail.com
License: BSD
Keywords: exif image photo rename metadata arrange rearrange catalogue
Platform: UNKNOWN
Classifier: Development Status :: 3 - Alpha
Classifier: Environment :: Console
Classifier: Intended Audience :: Developers
Classifier: Intended Audience :: End Users/Desktop
Classifier: License :: OSI Approved :: BSD License
Classifier: Operating System :: OS Independent
Classifier: Programming Language :: Python :: 3.4
Classifier: Topic :: Utilities
